MANIFEST.in
README.rst
VERSION
loremipsum.py
setup.py
py_loremipsum.egg-info/PKG-INFO
py_loremipsum.egg-info/SOURCES.txt
py_loremipsum.egg-info/dependency_links.txt
py_loremipsum.egg-info/entry_points.txt
py_loremipsum.egg-info/not-zip-safe
py_loremipsum.egg-info/requires.txt
py_loremipsum.egg-info/top_level.txt