Metadata-Version: 1.2
Name: py-loremipsum
Version: 1.1.0
Summary: Python module for generating placeholder text using the https://loripsum.net/ API
Home-page: https://github.com/connordelacruz/py-loremipsum/
Author: Connor de la Cruz
Author-email: connor.c.delacruz@gmail.com
License: MIT
Download-URL: https://github.com/connordelacruz/py-loremipsum/archive/1.1.0.tar.gz
Project-URL: Documentation, https://connordelacruz.com/py-loremipsum/
Project-URL: Source, https://github.com/connordelacruz/py-loremipsum/
Platform: UNKNOWN
Classifier: Intended Audience :: Developers
Classifier: License :: OSI Approved :: MIT License
Classifier: Programming Language :: Python
Classifier: Programming Language :: Python :: 3
Classifier: Topic :: Software Development :: Testing
Classifier: Topic :: Utilities
Classifier: Development Status :: 5 - Production/Stable
